{"name":"glium","counts":{"deprecated":0,"unstable":0,"stable":639,"unmarked":3030},"submodules":[{"name":"backend","counts":{"deprecated":0,"unstable":0,"stable":6,"unmarked":54},"submodules":[{"name":"glutin_backend","counts":{"deprecated":0,"unstable":0,"stable":5,"unmarked":26},"submodules":[]}]},{"name":"buffer","counts":{"deprecated":0,"unstable":0,"stable":13,"unmarked":62},"submodules":[]},{"name":"debug","counts":{"deprecated":0,"unstable":0,"stable":11,"unmarked":28},"submodules":[]},{"name":"draw_parameters","counts":{"deprecated":0,"unstable":0,"stable":54,"unmarked":114},"submodules":[]},{"name":"framebuffer","counts":{"deprecated":0,"unstable":0,"stable":8,"unmarked":89},"submodules":[]},{"name":"glutin","counts":{"deprecated":0,"unstable":0,"stable":55,"unmarked":321},"submodules":[]},{"name":"index","counts":{"deprecated":0,"unstable":0,"stable":15,"unmarked":54},"submodules":[]},{"name":"pixel_buffer","counts":{"deprecated":0,"unstable":0,"stable":0,"unmarked":9},"submodules":[]},{"name":"program","counts":{"deprecated":0,"unstable":0,"stable":24,"unmarked":15},"submodules":[]},{"name":"render_buffer","counts":{"deprecated":0,"unstable":0,"stable":0,"unmarked":1},"submodules":[]},{"name":"texture","counts":{"deprecated":0,"unstable":0,"stable":350,"unmarked":1811},"submodules":[]},{"name":"uniforms","counts":{"deprecated":0,"unstable":0,"stable":38,"unmarked":260},"submodules":[]},{"name":"vertex","counts":{"deprecated":0,"unstable":0,"stable":10,"unmarked":84},"submodules":[]}]}